qxenonsign/__init__.py
qxenonsign/core.py
qxenonsign/pyarmor_runtime_000000/__init__.py
fourchainsqtest-1.0.8.dist-info/METADATA
fourchainsqtest-1.0.8.dist-info/WHEEL
fourchainsqtest-1.0.8.dist-info/top_level.txt
fourchainsqtest-1.0.8.dist-info/RECORD
