Metadata-Version: 2.4
Name: fourchainsQtest
Version: 1.0.8
Summary: fourchainsQtest
Author: fourchains
Author-email: fourchains.work@gmail.com
Classifier: Programming Language :: Python :: 3
Classifier: License :: OSI Approved :: MIT License
Classifier: Operating System :: OS Independent
Requires-Python: >=3.7
Requires-Dist: numpy
Requires-Dist: requests
Requires-Dist: pydantic
Requires-Dist: pyngrok
Requires-Dist: flask
Dynamic: author
Dynamic: author-email
Dynamic: classifier
Dynamic: description-content-type
Dynamic: requires-dist
Dynamic: requires-python
Dynamic: summary
